multiphysics/__init__.py
multiphysics-0.0.3.dist-info/licenses/LICENSE
multiphysics-0.0.3.dist-info/METADATA
multiphysics-0.0.3.dist-info/WHEEL
multiphysics-0.0.3.dist-info/top_level.txt
multiphysics-0.0.3.dist-info/RECORD
