Metadata-Version: 2.4
Name: multiphysics
Version: 0.0.3
Summary: A differentiable multiphysics simulation code
Author-email: Philip Mocz <philip.mocz@gmail.com>
License:                                  Apache License
Project-URL: Documentation, https://multiphysics.readthedocs.io
Project-URL: Homepage, https://github.com/multiphysicslabs/multiphysics
Requires-Python: >=3.12
License-File: LICENSE
Requires-Dist: jax
Requires-Dist: numpy
Dynamic: license-file
